{"_type":"export","__export_format":4,"__export_date":"2021-11-01T16:14:03.113Z","__export_source":"insomnia.desktop.app:v2021.6.0","resources":[{"_id":"req_a09549271ec94e52ba0bfb2c7e49cecc","parentId":"fld_b0fa81f0299a4ae7a74450bd2c351b3f","modified":1635776324584,"created":1635519505881,"url":"{{ _.URL }}/users","name":"Get all users","description":"","method":"GET","body":{},"parameters":[],"headers":[{"name":"Accept","value":"{{ _.accept }}","id":"pair_93034a0c09274a83a5b13c259300c921"},{"name":"Content-Type","value":"{{ _['content-type'] }}","id":"pair_e662f4a5097d40c79a77708cff72cc96"}],"authentication":{"type":"bearer","disabled":false,"token":"{{ _.token }}","prefix":""},"metaSortKey":-1635519505881,"isPrivate":false,"settingStoreCookies":true,"settingSendCookies":true,"settingDisableRenderRequestBody":false,"settingEncodeUrl":true,"settingRebuildPath":true,"settingFollowRedirects":"global","_type":"request"},{"_id":"fld_b0fa81f0299a4ae7a74450bd2c351b3f","parentId":"fld_ba5b5571cdd041e2be2756d1f1b755f1","modified":1635519505886,"created":1635519505886,"name":"Users","description":"","environment":{},"environmentPropertyOrder":null,"metaSortKey":-1635519505886,"_type":"request_group"},{"_id":"fld_ba5b5571cdd041e2be2756d1f1b755f1","parentId":"wrk_b8fa53be6b954274915fb4ba8e12b3d0","modified":1635519511276,"created":1635519511276,"name":"CRUD","description":"","environment":{},"environmentPropertyOrder":null,"metaSortKey":-1635519511276,"_type":"request_group"},{"_id":"wrk_b8fa53be6b954274915fb4ba8e12b3d0","parentId":null,"modified":1635783197653,"created":1635519154318,"name":"API Platform Template","description":"","scope":"collection","_type":"workspace"},{"_id":"req_4d5adf7dff154ff491ad1db5136c087b","parentId":"fld_b0fa81f0299a4ae7a74450bd2c351b3f","modified":1635783007627,"created":1635519505877,"url":"{{ _.URL }}/users","name":"Post one user","description":"","method":"POST","body":{"mimeType":"application/json","text":"{\n    \"email\": \"aya@gmail.com\",\n    \"password\": \"C|+-rZ\\\"+<\\\\Nc3vTOCd\"\n}"},"parameters":[],"headers":[{"name":"Accept","value":"{{ _.accept }}","id":"pair_17179cb5dd6c40eebc21fe363ed2c92d"},{"name":"Content-Type","value":"{{ _['content-type'] }}","id":"pair_8467d8e77c1a41988ba5944d51b85550"}],"authentication":{},"metaSortKey":-1635519505877,"isPrivate":false,"settingStoreCookies":true,"settingSendCookies":true,"settingDisableRenderRequestBody":false,"settingEncodeUrl":true,"settingRebuildPath":true,"settingFollowRedirects":"global","_type":"request"},{"_id":"req_c14872a704024d4cabb4e04c2ecef7d9","parentId":"fld_b0fa81f0299a4ae7a74450bd2c351b3f","modified":1635783012336,"created":1635519505873,"url":"{{ _.URL }}/users/13","name":"Get one user","description":"","method":"GET","body":{},"parameters":[],"headers":[{"name":"Accept","value":"{{ _.accept }}","id":"pair_3810a63294d44102828bd3c10d16cf5a"},{"name":"Content-Type","value":"{{ _['content-type'] }}","id":"pair_b1bde894269f499a86b58090d5a1e5f2"}],"authentication":{"type":"bearer","disabled":false,"token":"{{ _.token }}","prefix":""},"metaSortKey":-1635519505873,"isPrivate":false,"settingStoreCookies":true,"settingSendCookies":true,"settingDisableRenderRequestBody":false,"settingEncodeUrl":true,"settingRebuildPath":true,"settingFollowRedirects":"global","_type":"request"},{"_id":"req_6846ed936b4e4b55b19ef7a220f35ed0","parentId":"fld_b0fa81f0299a4ae7a74450bd2c351b3f","modified":1635783013151,"created":1635519505870,"url":"{{ _.URL }}/users/13","name":"Put one user","description":"","method":"PUT","body":{"mimeType":"application/json","text":"{\n    \"email\": \"put@mail.com\"\n}"},"parameters":[],"headers":[{"name":"Accept","value":"{{ _.accept }}","id":"pair_9ca7de9e208945628a93e4267a321c9b"},{"name":"Content-Type","value":"{{ _['content-type'] }}","id":"pair_db5eee7caab045698efddc10b3826dd3"}],"authentication":{"type":"bearer","disabled":false,"token":"{{ _.token }}","prefix":""},"metaSortKey":-1635519505870,"isPrivate":false,"settingStoreCookies":true,"settingSendCookies":true,"settingDisableRenderRequestBody":false,"settingEncodeUrl":true,"settingRebuildPath":true,"settingFollowRedirects":"global","_type":"request"},{"_id":"req_109a61013be04ac6b044bbb9f35fe424","parentId":"fld_b0fa81f0299a4ae7a74450bd2c351b3f","modified":1635783014041,"created":1635519505866,"url":"{{ _.URL }}/users/13","name":"Patch one user","description":"","method":"PATCH","body":{"mimeType":"application/json","text":"{\n    \"email\": \"patch@mail.com\"\n}"},"parameters":[],"headers":[{"name":"Accept","value":"{{ _.accept }}","id":"pair_297420b5255b40f0af7bdee2e7e7760a"},{"name":"Content-Type","value":"{{ _['content-type'] }}","id":"pair_17f9e7d14ea74545b06c518ada2cc837"}],"authentication":{"type":"bearer","disabled":false,"token":"{{ _.token }}","prefix":""},"metaSortKey":-1635519505866,"isPrivate":false,"settingStoreCookies":true,"settingSendCookies":true,"settingDisableRenderRequestBody":false,"settingEncodeUrl":true,"settingRebuildPath":true,"settingFollowRedirects":"global","_type":"request"},{"_id":"req_a0840d96bff343f9a800b4c834eb076d","parentId":"fld_b0fa81f0299a4ae7a74450bd2c351b3f","modified":1635783014903,"created":1635519505862,"url":"{{ _.URL }}/users/13","name":"Delete one user","description":"","method":"DELETE","body":{"mimeType":"","text":""},"parameters":[],"headers":[{"name":"Accept","value":"{{ _.accept }}","id":"pair_49197d3e68a94c84a71b584dfacd89a3"},{"name":"Content-Type","value":"{{ _['content-type'] }}","id":"pair_dbfa95441da84b58862f7a3e9d5e270c"}],"authentication":{"type":"bearer","disabled":false,"token":"{{ _.token }}","prefix":""},"metaSortKey":-1635519505862,"isPrivate":false,"settingStoreCookies":true,"settingSendCookies":true,"settingDisableRenderRequestBody":false,"settingEncodeUrl":true,"settingRebuildPath":true,"settingFollowRedirects":"global","_type":"request"},{"_id":"req_c1427156ee774b30b8a143b99b8fe9ee","parentId":"fld_507d1b46ab4844ef9b7a037c697527d5","modified":1635783016433,"created":1635519505826,"url":"{{ _.URL }}/animations","name":"Get all animation","description":"","method":"GET","body":{},"parameters":[{"id":"pair_c966d1e1412b48e5aee3fe170b4b1cd7","name":"title","value":"Nulla","description":"","disabled":true},{"id":"pair_d9af9f0654fd4094906c703e65b19b68","name":"users","value":"3","description":""}],"headers":[{"name":"Accept","value":"{{ _.accept }}","id":"pair_eff87915cb884a40a714776f6fcc1dce"},{"name":"Content-Type","value":"{{ _['content-type'] }}","id":"pair_3f01e84dada9464cb5926e6045294cad"}],"authentication":{},"metaSortKey":-1635519505826,"isPrivate":false,"settingStoreCookies":true,"settingSendCookies":true,"settingDisableRenderRequestBody":false,"settingEncodeUrl":true,"settingRebuildPath":true,"settingFollowRedirects":"global","_type":"request"},{"_id":"fld_507d1b46ab4844ef9b7a037c697527d5","parentId":"fld_ba5b5571cdd041e2be2756d1f1b755f1","modified":1635519505829,"created":1635519505829,"name":"Animations","description":"","environment":{},"environmentPropertyOrder":null,"metaSortKey":-1635519505829,"_type":"request_group"},{"_id":"req_d06c31beef064e3fa284f4a9c625d719","parentId":"fld_507d1b46ab4844ef9b7a037c697527d5","modified":1635783017396,"created":1635519505821,"url":"{{ _.URL }}/animations","name":"Post one animation","description":"","method":"POST","body":{"mimeType":"application/json","text":"{\n  \"title\": \"test\",\n  \"shortDescription\": \"test\",\n  \"longDescription\": \"test\",\n  \"publicationDate\": \"2008-06-18 06:49:37\"\n}"},"parameters":[],"headers":[{"name":"Accept","value":"{{ _.accept }}","id":"pair_28e13cad3003445294c8baeb96a6256a"},{"name":"Content-Type","value":"{{ _['content-type'] }}","id":"pair_7426fda68ae04369b3f9ed8483735c55"}],"authentication":{"type":"bearer","disabled":false,"token":"{{ _.token }}","prefix":""},"metaSortKey":-1635519505821,"isPrivate":false,"settingStoreCookies":true,"settingSendCookies":true,"settingDisableRenderRequestBody":false,"settingEncodeUrl":true,"settingRebuildPath":true,"settingFollowRedirects":"global","_type":"request"},{"_id":"req_2cffdfe00c744ba385453e8c59dd6bd2","parentId":"fld_507d1b46ab4844ef9b7a037c697527d5","modified":1635783018196,"created":1635519505817,"url":"{{ _.URL }}/animations/1643","name":"Get one animation","description":"","method":"GET","body":{},"parameters":[],"headers":[{"name":"Accept","value":"{{ _.accept }}","id":"pair_171ccbec32da4256a6309c9b898d9c96"},{"name":"Content-Type","value":"{{ _['content-type'] }}","id":"pair_3a91b79aeecc42ee8ec62e0c9a4ff196"}],"authentication":{},"metaSortKey":-1635519505817,"isPrivate":false,"settingStoreCookies":true,"settingSendCookies":true,"settingDisableRenderRequestBody":false,"settingEncodeUrl":true,"settingRebuildPath":true,"settingFollowRedirects":"global","_type":"request"},{"_id":"req_cf75d6f7df6f42d2b8a74c667209fceb","parentId":"fld_507d1b46ab4844ef9b7a037c697527d5","modified":1635783019047,"created":1635519505813,"url":"{{ _.URL }}/animations/1964","name":"Put one animation","description":"","method":"PUT","body":{"mimeType":"application/json","text":"{\n    \"type\": \"/api/types/3\"\n}\n"},"parameters":[],"headers":[{"name":"Accept","value":"{{ _.accept }}","id":"pair_e3b9f1b9489242f4812b066f49f79398"},{"name":"Content-Type","value":"{{ _['content-type'] }}","id":"pair_9b773420308d4d8e9cc8b79737e13366"}],"authentication":{"type":"bearer","disabled":false,"token":"{{ _.token }}","prefix":""},"metaSortKey":-1635519505813,"isPrivate":false,"settingStoreCookies":true,"settingSendCookies":true,"settingDisableRenderRequestBody":false,"settingEncodeUrl":true,"settingRebuildPath":true,"settingFollowRedirects":"global","_type":"request"},{"_id":"req_dbec791ed5a749d9998bcc48a2a3d5e5","parentId":"fld_507d1b46ab4844ef9b7a037c697527d5","modified":1635783075519,"created":1635519505810,"url":"{{ _.URL }}/animations/1855","name":"Patch one animation","description":"","method":"PATCH","body":{"mimeType":"application/json","text":"{\n  \"type\": \"api/types/1\"\n}"},"parameters":[],"headers":[{"name":"Accept","value":"{{ _.accept }}","id":"pair_8bfff973f8cd4579b1cc216b5c9fcca0"},{"name":"Content-Type","value":"{{ _['content-type'] }}","id":"pair_d9c3a77e5fb34f2eabb3bc62e08d1445"}],"authentication":{"type":"bearer","disabled":false,"token":"{{ _.token }}","prefix":""},"metaSortKey":-1635519505810,"isPrivate":false,"settingStoreCookies":true,"settingSendCookies":true,"settingDisableRenderRequestBody":false,"settingEncodeUrl":true,"settingRebuildPath":true,"settingFollowRedirects":"global","_type":"request"},{"_id":"req_0ccdbb13c96f4b7595287d77927a96b1","parentId":"fld_507d1b46ab4844ef9b7a037c697527d5","modified":1635783020708,"created":1635519505807,"url":"{{ _.URL }}/animations/120","name":"Delete one animation","description":"","method":"DELETE","body":{"mimeType":"application/json","text":"{\n  \"title\": \"modifier\",\n  \"shortDescription\": \"modifier\",\n  \"longDescription\": \"modifier\"\n }"},"parameters":[],"headers":[{"name":"Accept","value":"{{ _.accept }}","id":"pair_242f091328654796a24cde01d16d67c2"},{"name":"Content-Type","value":"{{ _['content-type'] }}","id":"pair_3ca5cfdf310a424ea524d35e0a22678e"}],"authentication":{"type":"bearer","disabled":false,"token":"{{ _.token }}","prefix":""},"metaSortKey":-1635519505808.5,"isPrivate":false,"settingStoreCookies":true,"settingSendCookies":true,"settingDisableRenderRequestBody":false,"settingEncodeUrl":true,"settingRebuildPath":true,"settingFollowRedirects":"global","_type":"request"},{"_id":"req_ce126ef3d8a747389cd5c646a0fe5526","parentId":"fld_e3103f208c174fc4984f35bd0c78f6b0","modified":1635783022200,"created":1635519505784,"url":"{{ _.URL }}/media","name":"Get all medias","description":"","method":"GET","body":{},"parameters":[],"headers":[],"authentication":{"type":"bearer","disabled":false,"token":"{{ _.token }}","prefix":""},"metaSortKey":-1635519505784,"isPrivate":false,"settingStoreCookies":true,"settingSendCookies":true,"settingDisableRenderRequestBody":false,"settingEncodeUrl":true,"settingRebuildPath":true,"settingFollowRedirects":"global","_type":"request"},{"_id":"fld_e3103f208c174fc4984f35bd0c78f6b0","parentId":"fld_ba5b5571cdd041e2be2756d1f1b755f1","modified":1635519505785,"created":1635519505785,"name":"Medias","description":"","environment":{},"environmentPropertyOrder":null,"metaSortKey":-1635519505785,"_type":"request_group"},{"_id":"req_f7dbda019fd648a4b394e6c022ee3f66","parentId":"fld_e3103f208c174fc4984f35bd0c78f6b0","modified":1635783074238,"created":1635519505782,"url":"{{ _.URL }}/media/8","name":"Get one media","description":"","method":"GET","body":{},"parameters":[],"headers":[],"authentication":{"type":"bearer","disabled":false,"token":"{{ _.token }}","prefix":""},"metaSortKey":-1635519505782,"isPrivate":false,"settingStoreCookies":true,"settingSendCookies":true,"settingDisableRenderRequestBody":false,"settingEncodeUrl":true,"settingRebuildPath":true,"settingFollowRedirects":"global","_type":"request"},{"_id":"req_b2137641729a4d1c8e9134b8b9c21bf8","parentId":"fld_e3103f208c174fc4984f35bd0c78f6b0","modified":1635783027498,"created":1635519505782,"url":"{{ _.URL }}/media","name":"Post one media","description":"","method":"POST","body":{"params":[{"type":"file","name":"file","disabled":false,"fileName":"/home/zalbani/Pictures/julien-kaspar-finalcomp-720p.jpg","id":"pair_a6cbf0a8a7e943e4a3a4661909b8ebf4"},{"type":"text","name":"title","disabled":false,"value":"test","id":"pair_7fd9099864644c5ca3f468ea997200a1"},{"type":"text","name":"legend","disabled":false,"value":"test","id":"pair_71b08e188e91429482450bd8d515ff91"}],"mimeType":"multipart/form-data"},"parameters":[],"headers":[],"authentication":{"type":"bearer","disabled":false,"token":"{{ _.token }}","prefix":""},"metaSortKey":-1635519505782,"isPrivate":false,"settingStoreCookies":true,"settingSendCookies":true,"settingDisableRenderRequestBody":false,"settingEncodeUrl":true,"settingRebuildPath":true,"settingFollowRedirects":"global","_type":"request"},{"_id":"req_c5538f3a367042ae8f26df7c237e22ae","parentId":"fld_e3103f208c174fc4984f35bd0c78f6b0","modified":1635783076999,"created":1635519505781,"url":"{{ _.URL }}/media/8?_method=PUT","name":"Put one media ","description":"","method":"POST","body":{"params":[{"type":"file","name":"file","disabled":false,"fileName":"/home/zalbani/Pictures/Ydays/logo.png","id":"pair_56299abd9e594e6abad9a92bbdfc2b1e"},{"type":"text","name":"title","disabled":false,"value":"Tchao","id":"pair_c4cf69bc0d9b4713b2ccca0ef98f50c6"},{"type":"text","name":"target","disabled":false,"value":"Slt","id":"pair_39fb7e76bab340baa44625a0fe905fa8"}],"mimeType":"multipart/form-data"},"parameters":[],"headers":[],"authentication":{"type":"bearer","disabled":false,"token":"{{ _.token }}","prefix":""},"metaSortKey":-1635519505781,"isPrivate":false,"settingStoreCookies":true,"settingSendCookies":true,"settingDisableRenderRequestBody":false,"settingEncodeUrl":true,"settingRebuildPath":true,"settingFollowRedirects":"global","_type":"request"},{"_id":"req_3af1833bda5d4af39b0cb35abb13333a","parentId":"fld_e3103f208c174fc4984f35bd0c78f6b0","modified":1635783077751,"created":1635519505780,"url":"{{ _.URL }}/media/8","name":"Patch one media","description":"","method":"PATCH","body":{"mimeType":"application/json","text":"{\n  \"title\": \"new title\",\n  \"legend\": \"new wqdasx\"\n}"},"parameters":[],"headers":[{"id":"pair_4ec4a3ca85b645b5be50f6f8d34c67c8","name":"accept","value":"{{ _.accept }}","description":""},{"name":"Content-Type","value":"{{ _['content-type'] }}","id":"pair_99b1b4d40335436092f32353ea67894b"}],"authentication":{"type":"bearer","disabled":false,"token":"{{ _.token }}","prefix":""},"metaSortKey":-1635519505780,"isPrivate":false,"settingStoreCookies":true,"settingSendCookies":true,"settingDisableRenderRequestBody":false,"settingEncodeUrl":true,"settingRebuildPath":true,"settingFollowRedirects":"global","_type":"request"},{"_id":"req_2fdbc3471ce74eacb58b0561d611ea79","parentId":"fld_e3103f208c174fc4984f35bd0c78f6b0","modified":1635783078684,"created":1635519505779,"url":"{{ _.URL }}/media/5","name":"Delete one media","description":"","method":"DELETE","body":{},"parameters":[],"headers":[],"authentication":{"type":"bearer","disabled":false,"token":"{{ _.token }}","prefix":""},"metaSortKey":-1635519505779,"isPrivate":false,"settingStoreCookies":true,"settingSendCookies":true,"settingDisableRenderRequestBody":false,"settingEncodeUrl":true,"settingRebuildPath":true,"settingFollowRedirects":"global","_type":"request"},{"_id":"req_c6a33c53c8b343249f5dadb9e3fa0892","parentId":"fld_6679fd35ccf04114ba9d2316d819ba59","modified":1635783203141,"created":1635519505776,"url":"{{ _.URL }}/logs","name":"Get all logs","description":"","method":"GET","body":{},"parameters":[],"headers":[{"name":"Accept","value":"{{ _.accept }}","id":"pair_87df6918a87d48009f56d0354784a6e4"},{"name":"Content-Type","value":"{{ _['content-type'] }}","id":"pair_c7f4f495d2774c2aa7aaebd64babefcb"}],"authentication":{"type":"bearer","disabled":false,"token":"{{ _.token }}","prefix":""},"metaSortKey":-1635519505776,"isPrivate":false,"settingStoreCookies":true,"settingSendCookies":true,"settingDisableRenderRequestBody":false,"settingEncodeUrl":true,"settingRebuildPath":true,"settingFollowRedirects":"global","_type":"request"},{"_id":"fld_6679fd35ccf04114ba9d2316d819ba59","parentId":"fld_ba5b5571cdd041e2be2756d1f1b755f1","modified":1635519505778,"created":1635519505778,"name":"Logs","description":"","environment":{},"environmentPropertyOrder":null,"metaSortKey":-1635519505778,"_type":"request_group"},{"_id":"req_7a31d82b1b1c424784bd60a1872c4896","parentId":"fld_6679fd35ccf04114ba9d2316d819ba59","modified":1635783171275,"created":1635519505775,"url":"{{ _.URL }}/logs/1","name":"Get one log","description":"","method":"GET","body":{},"parameters":[],"headers":[{"name":"Accept","value":"{{ _.accept }}","id":"pair_453222572f7844ff93c405b0bab2f64b"},{"name":"Content-Type","value":"{{ _['content-type'] }}","id":"pair_639db63659d74e389a7098ca597aac5e"}],"authentication":{"type":"bearer","disabled":false,"token":"{{ _.token }}","prefix":""},"metaSortKey":-1635519505775,"isPrivate":false,"settingStoreCookies":true,"settingSendCookies":true,"settingDisableRenderRequestBody":false,"settingEncodeUrl":true,"settingRebuildPath":true,"settingFollowRedirects":"global","_type":"request"},{"_id":"req_99ae2901a4f44476b975efa7171d54da","parentId":"fld_a8cd1b4ab7f548f4a252ba868c090ff6","modified":1635783167586,"created":1635519505773,"url":"{{ _.URL }}/emails","name":"Get all emails","description":"","method":"GET","body":{},"parameters":[],"headers":[{"name":"Accept","value":"{{ _.accept }}","id":"pair_15845aca68a44fdcbd56e67ae33a3108"},{"name":"Content-Type","value":"{{ _['content-type'] }}","id":"pair_3ef783720d824b7297ae2358a3acd79a"}],"authentication":{"type":"bearer","disabled":false,"token":"{{ _.token }}","prefix":""},"metaSortKey":-1635519505773,"isPrivate":false,"settingStoreCookies":true,"settingSendCookies":true,"settingDisableRenderRequestBody":false,"settingEncodeUrl":true,"settingRebuildPath":true,"settingFollowRedirects":"global","_type":"request"},{"_id":"fld_a8cd1b4ab7f548f4a252ba868c090ff6","parentId":"fld_ba5b5571cdd041e2be2756d1f1b755f1","modified":1635519505774,"created":1635519505774,"name":"Email","description":"","environment":{},"environmentPropertyOrder":null,"metaSortKey":-1635519505774,"_type":"request_group"},{"_id":"req_23ce2a5ed63f46708acc89d62d1c7f71","parentId":"fld_a8cd1b4ab7f548f4a252ba868c090ff6","modified":1635783168603,"created":1635519505773,"url":"{{ _.URL }}/emails","name":"Post email","description":"","method":"POST","body":{"mimeType":"application/json","text":"{\n  \"recipient\": \"pro.pierson.alban@gmail.com\",\n  \"subject\": \"last test befor push\",\n  \"content\": \"Le contenu est appropriaeint\"\n}"},"parameters":[],"headers":[{"name":"Accept","value":"{{ _.accept }}","id":"pair_7c358743b9944d848d9bd4f30758f596"},{"name":"Content-Type","value":"{{ _['content-type'] }}","id":"pair_a58f462b06994a2f97a9d87bad350602"}],"authentication":{"type":"bearer","disabled":false,"token":"{{ _.token }}","prefix":""},"metaSortKey":-1635519505773,"isPrivate":false,"settingStoreCookies":true,"settingSendCookies":true,"settingDisableRenderRequestBody":false,"settingEncodeUrl":true,"settingRebuildPath":true,"settingFollowRedirects":"global","_type":"request"},{"_id":"req_7d075589ea1f47839f384cfab7b4694b","parentId":"fld_a8cd1b4ab7f548f4a252ba868c090ff6","modified":1635783169386,"created":1635519505772,"url":"{{ _.URL }}/emails/1","name":"Get one email","description":"","method":"GET","body":{},"parameters":[],"headers":[{"name":"Accept","value":"{{ _.accept }}","id":"pair_3f57888b3de44b94bc5bcf201e005fba"},{"name":"Content-Type","value":"{{ _['content-type'] }}","id":"pair_987280ea0dc9489ca7c95b5eea01e9f3"}],"authentication":{"type":"bearer","disabled":false,"token":"{{ _.token }}","prefix":""},"metaSortKey":-1635519505772,"isPrivate":false,"settingStoreCookies":true,"settingSendCookies":true,"settingDisableRenderRequestBody":false,"settingEncodeUrl":true,"settingRebuildPath":true,"settingFollowRedirects":"global","_type":"request"},{"_id":"req_fa557294c13d42e88b11be82862db6fc","parentId":"fld_cbf608244975403d8e7816edb35c4fd0","modified":1635775159059,"created":1635520270878,"url":"{{ _.URL }}/users/current","name":"Get current user","description":"","method":"GET","body":{},"parameters":[],"headers":[{"name":"Content-Type","value":"{{ _['content-type'] }}","id":"pair_6ead959991794a95bbf2fb3c419ab93d"},{"name":"Accept","value":"{{ _.accept }}","id":"pair_a27ffa4efb324b70ba21afa5bdb8e9f5"}],"authentication":{"type":"bearer","disabled":false,"token":"{{ _.token }}","prefix":""},"metaSortKey":-1635520270878,"isPrivate":false,"settingStoreCookies":true,"settingSendCookies":true,"settingDisableRenderRequestBody":false,"settingEncodeUrl":true,"settingRebuildPath":true,"settingFollowRedirects":"global","_type":"request"},{"_id":"fld_cbf608244975403d8e7816edb35c4fd0","parentId":"fld_6d746eb3cc564391a1463969bc466422","modified":1635520270879,"created":1635520270879,"name":"User","description":"","environment":{},"environmentPropertyOrder":null,"metaSortKey":-1635520270879,"_type":"request_group"},{"_id":"fld_6d746eb3cc564391a1463969bc466422","parentId":"wrk_b8fa53be6b954274915fb4ba8e12b3d0","modified":1635520357212,"created":1635520272934,"name":"Custom","description":"","environment":{},"environmentPropertyOrder":null,"metaSortKey":-1635519511226,"_type":"request_group"},{"_id":"req_78db153ee97940929f42a0f7703ac4e0","parentId":"fld_cbf608244975403d8e7816edb35c4fd0","modified":1635775166052,"created":1635520270875,"url":"{{ _.URL }}/users/295/updateRole","name":"Change Role","description":"","method":"PATCH","body":{"mimeType":"","text":"{\n    \"roles\": [\"ROLE_ADMIN\"]\n}"},"parameters":[],"headers":[{"name":"Accept","value":"{{accept}}","id":"pair_a1e29857fb8540259c0ddef67b6e1342"},{"name":"Content-Type","value":"{{content-type}}","id":"pair_46922cc13b114b9ca2a782b6f84adf00"}],"authentication":{"type":"bearer","disabled":false,"token":"{{ _.token }}","prefix":""},"metaSortKey":-1635520270875,"isPrivate":false,"settingStoreCookies":true,"settingSendCookies":true,"settingDisableRenderRequestBody":false,"settingEncodeUrl":true,"settingRebuildPath":true,"settingFollowRedirects":"global","_type":"request"},{"_id":"req_8463dfa25e2a4d16baf656a16c4111d9","parentId":"fld_df70c6d8fa8c42f7899aab403d291c68","modified":1635775175698,"created":1635520270873,"url":"{{ _.URL }}/public/animations/1964/triggerSubscribtion?userId=382","name":"Subscribe to animation","description":"","method":"PATCH","body":{"mimeType":"","text":"{}"},"parameters":[],"headers":[{"name":"Accept","value":"{{accept}}","id":"pair_15fe9fec15b44c0eb800d8c65777648c"},{"name":"Content-Type","value":"{{content-type}}","id":"pair_e520e6d745944201abba221cd7b5a7ef"}],"authentication":{},"metaSortKey":-1635520270873,"isPrivate":false,"settingStoreCookies":true,"settingSendCookies":true,"settingDisableRenderRequestBody":false,"settingEncodeUrl":true,"settingRebuildPath":true,"settingFollowRedirects":"global","_type":"request"},{"_id":"fld_df70c6d8fa8c42f7899aab403d291c68","parentId":"fld_6d746eb3cc564391a1463969bc466422","modified":1635520270874,"created":1635520270874,"name":"Animation","description":"","environment":{},"environmentPropertyOrder":null,"metaSortKey":-1635520270874,"_type":"request_group"},{"_id":"req_9847e1d9acfb42f1bf3788d49f6de5b4","parentId":"fld_df70c6d8fa8c42f7899aab403d291c68","modified":1635775188047,"created":1635520270871,"url":"{{ _.URL }}/animations/1231/publish","name":"Publish animation","description":"","method":"PATCH","body":{"mimeType":"","text":"{}"},"parameters":[],"headers":[{"name":"Accept","value":"{{accept}}","id":"pair_d96d6300c844464e8927bb069dfc6791"},{"name":"Content-Type","value":"{{content-type}}","id":"pair_3b4af3b7f98e41358c5f1a12bd0e06e3"}],"authentication":{"type":"bearer","disabled":false,"token":"{{ _.token }}","prefix":""},"metaSortKey":-1635520270871,"isPrivate":false,"settingStoreCookies":true,"settingSendCookies":true,"settingDisableRenderRequestBody":false,"settingEncodeUrl":true,"settingRebuildPath":true,"settingFollowRedirects":"global","_type":"request"},{"_id":"req_e4e275e70c874f8385c070fd61475027","parentId":"fld_df70c6d8fa8c42f7899aab403d291c68","modified":1635775197078,"created":1635520270870,"url":"{{ _.URL }}/animations/1228/unPublish","name":"unPublish animation","description":"","method":"PATCH","body":{"mimeType":"","text":"{}"},"parameters":[],"headers":[{"name":"Accept","value":"{{accept}}","id":"pair_9950d25d326349b79b0432db0ab75aab"},{"name":"Content-Type","value":"{{content-type}}","id":"pair_3d98fa3fe0004811b7867ade3b39d6d2"}],"authentication":{"type":"bearer","disabled":false,"token":"{{ _.token }}","prefix":""},"metaSortKey":-1635520270870,"isPrivate":false,"settingStoreCookies":true,"settingSendCookies":true,"settingDisableRenderRequestBody":false,"settingEncodeUrl":true,"settingRebuildPath":true,"settingFollowRedirects":"global","_type":"request"},{"_id":"req_517923e986014506820a678ac412593f","parentId":"fld_6d746eb3cc564391a1463969bc466422","modified":1635775242002,"created":1635520270868,"url":"{{ _.URL }}/public/forgottenPasswords?email=aya@gmail.com","name":"Reset password","description":"","method":"GET","body":{"mimeType":"application/json","text":""},"parameters":[],"headers":[{"name":"Accept","value":"{{ _.accept }}","id":"pair_e720432621464f84936559ebfa80a5c7"},{"name":"Content-Type","value":"application/json","id":"pair_b4874f72c62b4455964876fc32bbc820"}],"authentication":{},"metaSortKey":-1635520270868,"isPrivate":false,"settingStoreCookies":true,"settingSendCookies":true,"settingDisableRenderRequestBody":false,"settingEncodeUrl":true,"settingRebuildPath":true,"settingFollowRedirects":"global","_type":"request"},{"_id":"req_577015cf0cd649d8bb315f9d1b05950a","parentId":"fld_6d746eb3cc564391a1463969bc466422","modified":1635775228963,"created":1635520270867,"url":"{{ _.URL }}/login","name":"Login","description":"","method":"POST","body":{"mimeType":"application/json","text":"{\n    \"username\": \"admin@mail.com\",\n    \"password\": \"password\"\n}"},"parameters":[],"headers":[{"name":"Accept","value":"{{ _.accept }}","id":"pair_00f727c1fc3f4267835faea9407f3747"},{"name":"Content-Type","value":"{{ _['content-type'] }}","id":"pair_10b26aebbc1e4415bf13e556c10d93b1"}],"authentication":{},"metaSortKey":-1635520270867,"isPrivate":false,"settingStoreCookies":true,"settingSendCookies":true,"settingDisableRenderRequestBody":false,"settingEncodeUrl":true,"settingRebuildPath":true,"settingFollowRedirects":"global","_type":"request"},{"_id":"env_f6476a72cc66a6090837a41be2699d219e272226","parentId":"wrk_b8fa53be6b954274915fb4ba8e12b3d0","modified":1635519840593,"created":1635519154322,"name":"Base Environment","data":{},"dataPropertyOrder":{},"color":null,"isPrivate":false,"metaSortKey":1635519154322,"_type":"environment"},{"_id":"jar_f6476a72cc66a6090837a41be2699d219e272226","parentId":"wrk_b8fa53be6b954274915fb4ba8e12b3d0","modified":1635519154323,"created":1635519154323,"name":"Default Jar","cookies":[],"_type":"cookie_jar"},{"_id":"spc_5b70b577f06e4ece82e7eac357f30379","parentId":"wrk_b8fa53be6b954274915fb4ba8e12b3d0","modified":1635519154319,"created":1635519154319,"fileName":"CRUD","contents":"","contentType":"yaml","_type":"api_spec"},{"_id":"env_1a62271d850345bd8bb04e416171bbad","parentId":"env_f6476a72cc66a6090837a41be2699d219e272226","modified":1635520345140,"created":1635519854691,"name":"Marine portfolio","data":{"URL":"http://127.0.0.1:8000/api","token":"eyJ0eXAiOiJKV1QiLCJhbGciOiJSUzI1NiJ9.eyJpYXQiOjE2MzU1MjAzMjksImV4cCI6MTYzNTg4MDMyOSwicm9sZXMiOlsiUk9MRV9BRE1JTiIsIlJPTEVfVVNFUiJdLCJ1c2VybmFtZSI6ImFkbWluQG1haWwuY29tIiwiY3JlYXRlZEF0Ijp7ImRhdGUiOiIyMDIxLTA5LTIwIDE0OjQxOjI5LjAwMDAwMCIsInRpbWV6b25lX3R5cGUiOjMsInRpbWV6b25lIjoiRXVyb3BlL0JlcmxpbiJ9fQ.cvBAYnNZ9iC2CN__Ox0fJnF2FY_oKBlbUCHDJvUrp-CfD7rt9bGbhpuYgPnqP4hZcmkOene2JAhaDmQs1zciT0qMqlRykClsQj9jjt6-Yt0iGcyO50IyFpHQWk1PQyVkmlAE0PLHBLm1WguTqhY0t0vWcJNpEf_S8-YoxabFw5uuVSP2HPII4-cl5P3peBImzQsPvyzhgGyMhk4IirTF3F4gykCTWH053_vACFwqCxm5CQoFhivXPlbqI7QyCnllePBrkzRw-Xw1vlxcUruJ-ZKv8h8xdt9f0Cm3NGIMoI_F_DnDhbkP5Ym5hEvpXZHw-6QBeRXotEO96A6bMsIKhA","content-type":"application/json","accept":"application/json"},"dataPropertyOrder":{"&":["URL","token","content-type","accept"]},"color":null,"isPrivate":false,"metaSortKey":1635519854691,"_type":"environment"}]}